migration_fixer/__init__.py
migration_fixer/apps.py
migration_fixer/utils.py
migration_fixer/management/__init__.py
migration_fixer/management/commands/__init__.py
migration_fixer/management/commands/makemigrations.py
migration_fixer/tests/__init__.py
migration_fixer/tests/test_utils.py
migration_fixer/tests/management/__init__.py
migration_fixer/tests/management/commands/__init__.py
migration_fixer/tests/management/commands/_constants.py
migration_fixer/tests/management/commands/_utils.py
migration_fixer/tests/management/commands/conftest.py
migration_fixer/tests/management/commands/test_makemigrations.py
django_migration_fixer-1.3.6.dist-info/LICENSE
django_migration_fixer-1.3.6.dist-info/METADATA
django_migration_fixer-1.3.6.dist-info/WHEEL
django_migration_fixer-1.3.6.dist-info/top_level.txt
django_migration_fixer-1.3.6.dist-info/RECORD
