Metadata-Version: 2.1
Name: django-migration-fixer
Version: 1.3.6
Summary: Resolve migration errors
Home-page: https://github.com/tj-django/django-migration-fixer
Author: Tonye Jack
Author-email: jtonye@ymail.com
License: MIT license
Project-URL: Source, https://github.com/tj-django/django-migration-fixer
Project-URL: Documentation, https://tj-django.github.io/django-migration-fixer
Keywords: migration fixer,django migrations,django migrations fixer,django migrations auto fix,migrations fix,migrations conflict resolver,django migrations,django migrations autofix
Platform: UNKNOWN
Classifier: Development Status :: 5 - Production/Stable
Classifier: Intended Audience :: Developers
Classifier: License :: OSI Approved :: MIT License
Classifier: Natural Language :: English
Classifier: Programming Language :: Python :: 3.6
Classifier: Programming Language :: Python :: 3.7
Classifier: Programming Language :: Python :: 3.8
Classifier: Programming Language :: Python :: 3.9
Classifier: Programming Language :: Python :: 3.10
Classifier: Programming Language :: Python :: Implementation :: CPython
Classifier: Programming Language :: Python :: Implementation :: PyPy
Classifier: Framework :: Django :: 1.11
Classifier: Framework :: Django :: 2.0
Classifier: Framework :: Django :: 2.1
Classifier: Framework :: Django :: 2.2
Classifier: Framework :: Django :: 3.0
Classifier: Framework :: Django :: 3.1
Classifier: Framework :: Django :: 3.2
Requires-Python: >=3.6
Requires-Dist: django
Requires-Dist: GitPython
Requires-Dist: typing-extensions (>=3.10.0.0)
Provides-Extra: deploy
Requires-Dist: bump2version ; extra == 'deploy'
Requires-Dist: readme-renderer[md] ; extra == 'deploy'
Provides-Extra: development
Requires-Dist: django ; extra == 'development'
Requires-Dist: GitPython ; extra == 'development'
Requires-Dist: typing-extensions (>=3.10.0.0) ; extra == 'development'
Requires-Dist: bump2version ; extra == 'development'
Requires-Dist: readme-renderer[md] ; extra == 'development'
Requires-Dist: pytest (>=3) ; extra == 'development'
Requires-Dist: pytest-django ; extra == 'development'
Requires-Dist: pytest-sugar ; extra == 'development'
Requires-Dist: pytest-mock ; extra == 'development'
Requires-Dist: pytest-git ; extra == 'development'
Requires-Dist: tox ; extra == 'development'
Requires-Dist: tox-gh-actions ; extra == 'development'
Requires-Dist: coverage ; extra == 'development'
Requires-Dist: pip-tools ; extra == 'development'
Requires-Dist: flake8 ; extra == 'development'
Requires-Dist: yamllint ; extra == 'development'
Requires-Dist: isort ; extra == 'development'
Requires-Dist: black ; extra == 'development'
Requires-Dist: mypy ; extra == 'development'
Provides-Extra: docs
Requires-Dist: mkautodoc ; extra == 'docs'
Requires-Dist: mkdocs (<1.5,>=1.4) ; extra == 'docs'
Requires-Dist: portray ; extra == 'docs'
Requires-Dist: mkdocs-material-extensions (>=1.0.3) ; extra == 'docs'
Requires-Dist: pygments (<2.14,>=2.13) ; extra == 'docs'
Requires-Dist: pymdown-extensions (<9.7,>=9.6) ; extra == 'docs'
Provides-Extra: lint
Requires-Dist: flake8 ; extra == 'lint'
Requires-Dist: yamllint ; extra == 'lint'
Requires-Dist: isort ; extra == 'lint'
Requires-Dist: black ; extra == 'lint'
Requires-Dist: mypy ; extra == 'lint'
Provides-Extra: test
Requires-Dist: pytest (>=3) ; extra == 'test'
Requires-Dist: pytest-django ; extra == 'test'
Requires-Dist: bump2version ; extra == 'test'
Requires-Dist: pytest-sugar ; extra == 'test'
Requires-Dist: pytest-mock ; extra == 'test'
Requires-Dist: pytest-git ; extra == 'test'
Requires-Dist: tox ; extra == 'test'
Requires-Dist: tox-gh-actions ; extra == 'test'
Requires-Dist: coverage ; extra == 'test'
Requires-Dist: pip-tools ; extra == 'test'
